{
  "condition": "minecraft:alternative",
  "terms": [
    {
      "condition": "minecraft:entity_properties",
      "entity": "this",
      "predicate": {
        "equipment": {
          "mainhand": {
            "tag": "dynamiclights:redstone_light"
          }
        }
      }
    },
    {
      "condition": "minecraft:entity_properties",
      "entity": "this",
      "predicate": {
        "equipment": {
          "offhand": {
            "tag": "dynamiclights:redstone_light"
          }
        }
      }
    },
    {
      "condition": "minecraft:entity_properties",
      "entity": "this",
      "predicate": {
        "equipment": {
          "head": {
            "tag": "dynamiclights:redstone_light"
          }
        }
      }
    },
    {
      "condition": "minecraft:entity_properties",
      "entity": "this",
      "predicate": {
        "equipment": {
          "mainhand": {
            "count": {
              "min": 1
            },
            "enchantments": [
              {
                "levels": {
                  "min": 1
                }
              }
            ]
          }
        }
      }
    },
    {
      "condition": "minecraft:entity_properties",
      "entity": "this",
      "predicate": {
        "equipment": {
          "offhand": {
            "count": {
              "min": 1
            },
            "enchantments": [
              {
                "levels": {
                  "min": 1
                }
              }
            ]
          }
        }
      }
    },
    {
      "condition": "minecraft:entity_properties",
      "entity": "this",
      "predicate": {
        "equipment": {
          "head": {
            "count": {
              "min": 1
            },
            "enchantments": [
              {
                "levels": {
                  "min": 1
                }
              }
            ]
          }
        }
      }
    },
    {
      "condition": "minecraft:entity_properties",
      "entity": "this",
      "predicate": {
        "equipment": {
          "chest": {
            "count": {
              "min": 1
            },
            "enchantments": [
              {
                "levels": {
                  "min": 1
                }
              }
            ]
          }
        }
      }
    },
    {
      "condition": "minecraft:entity_properties",
      "entity": "this",
      "predicate": {
        "equipment": {
          "legs": {
            "count": {
              "min": 1
            },
            "enchantments": [
              {
                "levels": {
                  "min": 1
                }
              }
            ]
          }
        }
      }
    },
    {
      "condition": "minecraft:entity_properties",
      "entity": "this",
      "predicate": {
        "equipment": {
          "feet": {
            "count": {
              "min": 1
            },
            "enchantments": [
              {
                "levels": {
                  "min": 1
                }
              }
            ]
          }
        }
      }
    }
  ]
}
